updatehnkcooler/Load.py
updatehnkcooler/__init__.py
updatehnkcooler/fields.py
updatehnkcooler/util.py
updatehnkcooler-0.1.1.dist-info/LICENSE.txt
updatehnkcooler-0.1.1.dist-info/METADATA
updatehnkcooler-0.1.1.dist-info/WHEEL
updatehnkcooler-0.1.1.dist-info/top_level.txt
updatehnkcooler-0.1.1.dist-info/RECORD
