Metadata-Version: 2.1
Name: updatehnkcooler
Version: 0.1.1
Summary: Update coolers info
Author: Eduardo Martinez
Author-email: eduardo.martinez.2117@gmail.com
Keywords: heineken,python,bigquery,storage,bucket
Classifier: Development Status :: 1 - Planning
Classifier: Intended Audience :: Developers
Classifier: Programming Language :: Python :: 3
Classifier: Operating System :: Unix
Classifier: Operating System :: MacOS :: MacOS X
Classifier: Operating System :: Microsoft :: Windows
License-File: LICENSE.txt
Requires-Dist: google-cloud-storage
Requires-Dist: google-cloud-bigquery
Requires-Dist: pytz
